[
	{
		"pk": 1,
		"model": "users.countries",
		"fields": {
			"countries": "Middle East"
		}
	},
	{
		"pk": 2,
		"model": "users.countries",
		"fields": {
			"countries": "Iran"
		}
	},
	{
		"pk": 3,
		"model": "users.countries",
		"fields": {
			"countries": "Syria"
		}
	},
	{
		"pk": 4,
		"model": "users.countries",
		"fields": {
			"countries": "Egypt"
		}
	},
	{
		"pk": 5,
		"model": "users.countries",
		"fields": {
			"countries": "Oman"
		}
	},
	{
		"pk": 6,
		"model": "users.countries",
		"fields": {
			"countries": "Saudi Arabia"
		}
	},
	{
		"pk": 7,
		"model": "users.countries",
		"fields": {
			"countries": "Yemen"
		}
	},
	{
		"pk": 8,
		"model": "users.countries",
		"fields": {
			"countries": "Africa"
		}
	},
	{
		"pk": 9,
		"model": "users.countries",
		"fields": {
			"countries": "Cameroon"
		}
	},
	{
		"pk": 10,
		"model": "users.countries",
		"fields": {
			"countries": "Sudan"
		}
	},
	{
		"pk": 11,
		"model": "users.countries",
		"fields": {
			"countries": "Zimbabwe"
		}
	},
	{
		"pk": 12,
		"model": "users.countries",
		"fields": {
			"countries": "Eritrea"
		}
	},
	{
		"pk": 13,
		"model": "users.countries",
		"fields": {
			"countries": "Chad"
		}
	},
	{
		"pk": 14,
		"model": "users.countries",
		"fields": {
			"countries": "Equatorial Guinea"
		}
	},
	{
		"pk": 15,
		"model": "users.countries",
		"fields": {
			"countries": "Gambia"
		}
	},
	{
		"pk": 16,
		"model": "users.countries",
		"fields": {
			"countries": "Burquina Faso"
		}
	},
	{
		"pk": 17,
		"model": "users.countries",
		"fields": {
			"countries": "Uganda"
		}
	},
	{
		"pk": 18,
		"model": "users.countries",
		"fields": {
			"countries": "Etheopia"
		}
	},
	{
		"pk": 19,
		"model": "users.countries",
		"fields": {
			"countries": "China"
		}
	}
]